opendr_toolkit-0.9.dist-info/WHEEL
opendr_toolkit-0.9.dist-info/top_level.txt
opendr_toolkit-0.9.dist-info/LICENSE
opendr_toolkit-0.9.dist-info/METADATA
opendr_toolkit-0.9.dist-info/RECORD
opendr/_version.py
opendr/__init__.py
opendr/engine/data.py
opendr/engine/target.py
opendr/engine/example_learner.py
opendr/engine/learners.py
opendr/engine/constants.py
opendr/engine/__init__.py
opendr/engine/datasets.py
opendr/perception/__init__.py
opendr/perception/object_detection_2d/__init__.py
opendr/perception/object_detection_2d/gem/gem_learner.py
opendr/perception/object_detection_2d/gem/__init__.py
opendr/perception/object_detection_2d/gem/algorithm/__init__.py
opendr/perception/object_detection_2d/gem/algorithm/engine.py
opendr/perception/object_detection_2d/gem/algorithm/models/mm_detr.py
opendr/perception/object_detection_2d/gem/algorithm/models/backbone_mobilenetv2.py
opendr/perception/object_detection_2d/gem/algorithm/models/__init__.py
opendr/perception/object_detection_2d/gem/algorithm/datasets/coco.py
opendr/perception/object_detection_2d/gem/algorithm/datasets/__init__.py
opendr/perception/object_detection_2d/gem/algorithm/datasets/transforms.py
opendr/perception/object_detection_2d/gem/algorithm/util/draw.py
opendr/perception/object_detection_2d/gem/algorithm/util/misc.py
opendr/perception/object_detection_2d/gem/algorithm/util/__init__.py
opendr/perception/object_detection_2d/gem/algorithm/util/sampler.py
opendr/perception/object_detection_2d/gem/algorithm/util/detect.py
opendr/perception/object_detection_2d/yolov3/yolov3_learner.py
opendr/perception/object_detection_2d/yolov3/__init__.py
opendr/perception/object_detection_2d/datasets/wider_person.py
opendr/perception/object_detection_2d/datasets/wider_face.py
opendr/perception/object_detection_2d/datasets/__init__.py
opendr/perception/object_detection_2d/datasets/transforms.py
opendr/perception/object_detection_2d/datasets/detection_dataset.py
opendr/perception/object_detection_2d/detr/detr_learner.py
opendr/perception/object_detection_2d/detr/__init__.py
opendr/perception/object_detection_2d/detr/algorithm/__init__.py
