Metadata-Version: 2.1
Name: opendr-toolkit
Version: 0.9
Summary: Open Deep Learning Toolkit for Robotics
Home-page: https://github.com/opendr-eu/opendr
Author: OpenDR consortium
Author-email: tefas@csd.auth.gr
License: LICENSE
Platform: UNKNOWN
Requires-Dist: Automat (==20.2.0)
Requires-Dist: Cython (==0.29.22)
Requires-Dist: Mako (==1.1.6)
Requires-Dist: Markdown (==3.3.6)
Requires-Dist: MarkupSafe (==2.0.1)
Requires-Dist: Pillow (==7.0.0)
Requires-Dist: PyWavelets (==1.2.0)
Requires-Dist: PyYAML (==5.3)
Requires-Dist: Rx (==3.2.0)
Requires-Dist: SQLAlchemy (==1.4.29)
Requires-Dist: Shapely (==1.8.0)
Requires-Dist: SoundFile (==0.10.3.post1)
Requires-Dist: Twisted (==21.7.0)
Requires-Dist: Werkzeug (==2.0.2)
Requires-Dist: absl-py (==1.0.0)
Requires-Dist: aiohttp (==3.8.1)
Requires-Dist: aiosignal (==1.2.0)
Requires-Dist: alembic (==1.7.5)
Requires-Dist: antlr4-python3-runtime (==4.8)
Requires-Dist: appdirs (==1.4.4)
Requires-Dist: async-timeout (==4.0.2)
Requires-Dist: attrs (==21.2.0)
Requires-Dist: audioread (==2.1.9)
Requires-Dist: autobahn (==21.11.1)
Requires-Dist: autocfg (==0.0.8)
Requires-Dist: autopage (==0.4.0)
Requires-Dist: av (==8.0.1)
Requires-Dist: bcolz (==1.2.1)
Requires-Dist: black (==21.4b2)
Requires-Dist: cachetools (==4.2.4)
Requires-Dist: catkin-pkg (==0.4.24)
Requires-Dist: catkin-tools (==0.8.2)
Requires-Dist: certifi (==2021.10.8)
Requires-Dist: cffi (==1.15.0)
Requires-Dist: charset-normalizer (==2.0.9)
Requires-Dist: click (==8.0.3)
Requires-Dist: cliff (==3.10.0)
Requires-Dist: cloudpickle (==1.5.0)
Requires-Dist: cmaes (==0.8.2)
Requires-Dist: cmd2 (==2.3.3)
Requires-Dist: colorlog (==6.6.0)
Requires-Dist: configparser (==5.2.0)
Requires-Dist: constantly (==15.1.0)
Requires-Dist: cryptography (==36.0.1)
Requires-Dist: cycler (==0.11.0)
Requires-Dist: cython-bbox (==0.1.3)
Requires-Dist: decorator (==5.1.0)
Requires-Dist: defusedxml (==0.7.1)
Requires-Dist: distro (==1.6.0)
Requires-Dist: dlib (==19.22.1)
Requires-Dist: docutils (==0.18.1)
Requires-Dist: easydict (==1.9)
Requires-Dist: empy (==3.3.4)
Requires-Dist: filterpy (==1.4.5)
Requires-Dist: flake8-import-order (==0.18.1)
Requires-Dist: flake8 (==4.0.1)
Requires-Dist: fonttools (==4.28.5)
Requires-Dist: frozenlist (==1.2.0)
Requires-Dist: fsspec (==2021.11.1)
Requires-Dist: future (==0.18.2)
Requires-Dist: fvcore (==0.1.5.post20211023)
Requires-Dist: gluoncv (==0.11.0b20210908)
Requires-Dist: google-auth-oauthlib (==0.4.6)
Requires-Dist: google-auth (==1.35.0)
Requires-Dist: graphviz (==0.8.4)
Requires-Dist: greenlet (==1.1.2)
Requires-Dist: grpcio (==1.43.0)
Requires-Dist: gym (==0.21.0)
Requires-Dist: h5py (==3.6.0)
Requires-Dist: hydra-core (==1.1.1)
Requires-Dist: hyperlink (==21.0.0)
Requires-Dist: idna (==3.3)
Requires-Dist: imageio (==2.6.0)
Requires-Dist: imantics (==0.1.12)
Requires-Dist: imgaug (==0.4.0)
Requires-Dist: importlib-metadata (==4.10.0)
Requires-Dist: importlib-resources (==5.4.0)
Requires-Dist: imutils (==0.5.4)
Requires-Dist: incremental (==21.3.0)
Requires-Dist: iniconfig (==1.1.1)
Requires-Dist: iopath (==0.1.8)
Requires-Dist: joblib (==1.0.1)
Requires-Dist: kiwisolver (==1.3.2)
Requires-Dist: lap (==0.4.0)
Requires-Dist: librosa (==0.8.0)
Requires-Dist: llvmlite (==0.31.0)
Requires-Dist: lxml (==4.7.1)
Requires-Dist: matplotlib (==2.2.2)
Requires-Dist: mccabe (==0.6.1)
Requires-Dist: motmetrics (==1.2.0)
Requires-Dist: multidict (==5.2.0)
Requires-Dist: munkres (==1.1.4)
Requires-Dist: mxnet-cu102 (==1.8.0)
Requires-Dist: mxnet (==1.8.0)
Requires-Dist: mypy-extensions (==0.4.3)
Requires-Dist: netifaces (==0.11.0)
Requires-Dist: networkx (==2.6.3)
Requires-Dist: numba (==0.48.0)
Requires-Dist: numpy (==1.21.5)
Requires-Dist: oauthlib (==3.1.1)
Requires-Dist: omegaconf (==2.1.1)
Requires-Dist: onnx (==1.8.0)
Requires-Dist: onnxruntime (==1.3.0)
Requires-Dist: opencv-python (==4.5.1.48)
Requires-Dist: optuna (==2.10.0)
Requires-Dist: osrf-pycommon (==1.0.0)
Requires-Dist: packaging (==21.3)
Requires-Dist: pandas (==1.2.0)
Requires-Dist: pathspec (==0.9.0)
Requires-Dist: pbr (==5.8.0)
Requires-Dist: pkg-resources (==0.0.0)
Requires-Dist: plotly (==5.5.0)
Requires-Dist: pluggy (==1.0.0)
Requires-Dist: pooch (==1.5.2)
Requires-Dist: portalocker (==2.3.2)
Requires-Dist: prettytable (==2.5.0)
Requires-Dist: progress (==1.5)
Requires-Dist: protobuf (==3.11.3)
Requires-Dist: psutil (==5.8.0)
Requires-Dist: py-cpuinfo (==8.0.0)
Requires-Dist: py (==1.11.0)
Requires-Dist: pyasn1-modules (==0.2.8)
Requires-Dist: pyasn1 (==0.4.8)
Requires-Dist: pybind11 (==2.6.2)
Requires-Dist: pycodestyle (==2.8.0)
Requires-Dist: pycparser (==2.21)
Requires-Dist: pydot (==1.4.2)
Requires-Dist: pyflakes (==2.4.0)
Requires-Dist: pyglet (==1.5.16)
Requires-Dist: pyparsing (==3.0.6)
Requires-Dist: pyperclip (==1.8.2)
Requires-Dist: pyqtgraph (==0.12.3)
Requires-Dist: pytest-benchmark (==3.4.1)
Requires-Dist: pytest (==6.2.5)
Requires-Dist: python-dateutil (==2.8.2)
Requires-Dist: pytorch-lightning (==1.2.3)
Requires-Dist: pytz (==2021.3)
Requires-Dist: regex (==2021.11.10)
Requires-Dist: requests-oauthlib (==1.3.0)
Requires-Dist: requests (==2.26.0)
Requires-Dist: resampy (==0.2.2)
Requires-Dist: rosdep (==0.21.0)
Requires-Dist: rosdistro (==0.8.3)
Requires-Dist: roslibpy (==1.2.1)
Requires-Dist: rospkg (==1.3.0)
Requires-Dist: rsa (==4.8)
Requires-Dist: scikit-image (==0.16.2)
Requires-Dist: scikit-learn (==0.21.3)
Requires-Dist: scipy (==1.7.3)
Requires-Dist: six (==1.16.0)
Requires-Dist: sklearn (==0.0)
Requires-Dist: stable-baselines3 (==1.1.0)
Requires-Dist: stevedore (==3.5.0)
Requires-Dist: tabulate (==0.8.9)
Requires-Dist: tenacity (==8.0.1)
Requires-Dist: tensorboard-data-server (==0.6.1)
Requires-Dist: tensorboard-plugin-wit (==1.8.0)
Requires-Dist: tensorboard (==2.4.1)
Requires-Dist: tensorboardX (==2.0)
Requires-Dist: termcolor (==1.1.0)
Requires-Dist: toml (==0.10.2)
Requires-Dist: torch (==1.7.1)
Requires-Dist: torchvision (==0.8.2)
Requires-Dist: tqdm (==4.54.0)
Requires-Dist: trimesh (==3.5.23)
Requires-Dist: txaio (==21.2.1)
Requires-Dist: typing-extensions (==4.0.1)
Requires-Dist: urllib3 (==1.26.7)
Requires-Dist: vcstool (==0.3.0)
Requires-Dist: wcwidth (==0.2.5)
Requires-Dist: xmljson (==0.2.1)
Requires-Dist: xmltodict (==0.12.0)
Requires-Dist: yacs (==0.1.8)
Requires-Dist: yarl (==1.7.2)
Requires-Dist: zipp (==3.6.0)
Requires-Dist: zope.interface (==5.4.0)
